{
  "name": "Minimal Kiwi Darker",
  "type": "dark",
  "semanticHighlighting": true,
  "colors": {
    "editor.background": "#0a0a0a",
    "editor.foreground": "#828989",
    "editorLineNumber.foreground": "#3a3a3a",
    "editorLineNumber.activeForeground": "#C3E88D",
    "editorCursor.foreground": "#C3E88D",
    "editor.selectionBackground": "#1a2a1a",
    "editor.selectionHighlightBackground": "#151a15",
    "editor.lineHighlightBackground": "#0f0f0f",
    "editor.wordHighlightBackground": "#1a2a1a88",
    "editor.wordHighlightStrongBackground": "#1a2a1a",
    "editor.findMatchBackground": "#2a3a2a",
    "editor.findMatchHighlightBackground": "#1a2a1a88",
    "editor.hoverHighlightBackground": "#1a2a1a",
    "editorBracketMatch.background": "#1a2a1a",
    "editorBracketMatch.border": "#C3E88D",
    "editorIndentGuide.background": "#1a1a1a",
    "editorIndentGuide.activeBackground": "#2a2a2a",
    "editorWhitespace.foreground": "#1a1a1a",
    "editorGroupHeader.tabsBackground": "#0a0a0a",
    "sideBar.background": "#0d0d0d",
    "sideBar.foreground": "#828989",
    "sideBar.border": "#1a1a1a",
    "sideBarTitle.foreground": "#C3E88D",
    "sideBarSectionHeader.background": "#0a0a0a",
    "sideBarSectionHeader.foreground": "#C3E88D",
    "sideBarSectionHeader.border": "#1a1a1a",
    "activityBar.background": "#080808",
    "activityBar.foreground": "#C3E88D",
    "activityBar.inactiveForeground": "#3a3a3a",
    "activityBar.border": "#1a1a1a",
    "activityBarBadge.background": "#C3E88D",
    "activityBarBadge.foreground": "#0a0a0a",
    "statusBar.background": "#080808",
    "statusBar.foreground": "#828989",
    "statusBar.border": "#1a1a1a",
    "statusBar.noFolderBackground": "#080808",
    "statusBar.debuggingBackground": "#2a2a1a",
    "statusBarItem.remoteBackground": "#1a2a1a",
    "statusBarItem.remoteForeground": "#C3E88D",
    "titleBar.activeBackground": "#0a0a0a",
    "titleBar.activeForeground": "#828989",
    "titleBar.inactiveBackground": "#080808",
    "titleBar.inactiveForeground": "#3a3a3a",
    "titleBar.border": "#1a1a1a",
    "tab.activeBackground": "#0f0f0f",
    "tab.activeForeground": "#C3E88D",
    "tab.inactiveBackground": "#0a0a0a",
    "tab.inactiveForeground": "#5a5a5a",
    "tab.border": "#1a1a1a",
    "tab.activeBorder": "#C3E88D",
    "tab.hoverBackground": "#0d0d0d",
    "tab.unfocusedActiveForeground": "#828989",
    "tab.unfocusedInactiveForeground": "#3a3a3a",
    "panel.background": "#0a0a0a",
    "panel.border": "#1a1a1a",
    "panelTitle.activeBorder": "#C3E88D",
    "panelTitle.activeForeground": "#C3E88D",
    "panelTitle.inactiveForeground": "#5a5a5a",
    "terminal.background": "#0a0a0a",
    "terminal.foreground": "#828989",
    "terminal.ansiBlack": "#0a0a0a",
    "terminal.ansiRed": "#F07178",
    "terminal.ansiGreen": "#C3E88D",
    "terminal.ansiYellow": "#FFCB6B",
    "terminal.ansiBlue": "#82AAFF",
    "terminal.ansiMagenta": "#C792EA",
    "terminal.ansiCyan": "#89DDFF",
    "terminal.ansiWhite": "#828989",
    "terminal.ansiBrightBlack": "#3a3a3a",
    "terminal.ansiBrightRed": "#F07178",
    "terminal.ansiBrightGreen": "#C3E88D",
    "terminal.ansiBrightYellow": "#FFCB6B",
    "terminal.ansiBrightBlue": "#82AAFF",
    "terminal.ansiBrightMagenta": "#C792EA",
    "terminal.ansiBrightCyan": "#89DDFF",
    "terminal.ansiBrightWhite": "#EEFFFF",
    "list.activeSelectionBackground": "#1a2a1a",
    "list.activeSelectionForeground": "#C3E88D",
    "list.inactiveSelectionBackground": "#151515",
    "list.inactiveSelectionForeground": "#828989",
    "list.hoverBackground": "#0f0f0f",
    "list.focusBackground": "#1a2a1a",
    "list.highlightForeground": "#C3E88D",
    "input.background": "#0d0d0d",
    "input.foreground": "#828989",
    "input.border": "#1a1a1a",
    "input.placeholderForeground": "#3a3a3a",
    "inputOption.activeBorder": "#C3E88D",
    "inputValidation.errorBackground": "#2a1a1a",
    "inputValidation.errorBorder": "#F07178",
    "dropdown.background": "#0d0d0d",
    "dropdown.foreground": "#828989",
    "dropdown.border": "#1a1a1a",
    "button.background": "#C3E88D",
    "button.foreground": "#0a0a0a",
    "button.hoverBackground": "#B5DB7D",
    "badge.background": "#C3E88D",
    "badge.foreground": "#0a0a0a",
    "scrollbarSlider.background": "#1a1a1a88",
    "scrollbarSlider.hoverBackground": "#2a2a2a88",
    "scrollbarSlider.activeBackground": "#3a3a3a88",
    "editorWidget.background": "#0d0d0d",
    "editorWidget.border": "#1a1a1a",
    "editorSuggestWidget.background": "#0d0d0d",
    "editorSuggestWidget.border": "#1a1a1a",
    "editorSuggestWidget.foreground": "#828989",
    "editorSuggestWidget.highlightForeground": "#C3E88D",
    "editorSuggestWidget.selectedBackground": "#1a2a1a",
    "peekView.border": "#C3E88D",
    "peekViewEditor.background": "#0d0d0d",
    "peekViewEditor.matchHighlightBackground": "#2a3a2a",
    "peekViewResult.background": "#0a0a0a",
    "peekViewResult.matchHighlightBackground": "#2a3a2a",
    "peekViewResult.selectionBackground": "#1a2a1a",
    "peekViewTitle.background": "#0a0a0a",
    "peekViewTitleDescription.foreground": "#5a5a5a",
    "peekViewTitleLabel.foreground": "#C3E88D",
    "gitDecoration.modifiedResourceForeground": "#82AAFF",
    "gitDecoration.deletedResourceForeground": "#F07178",
    "gitDecoration.untrackedResourceForeground": "#C3E88D",
    "gitDecoration.ignoredResourceForeground": "#3a3a3a",
    "gitDecoration.conflictingResourceForeground": "#FFCB6B",
    "breadcrumb.background": "#0a0a0a",
    "breadcrumb.foreground": "#5a5a5a",
    "breadcrumb.focusForeground": "#C3E88D",
    "breadcrumb.activeSelectionForeground": "#C3E88D",
    "breadcrumbPicker.background": "#0d0d0d",
    "notificationCenter.border": "#1a1a1a",
    "notificationCenterHeader.background": "#0d0d0d",
    "notifications.background": "#0d0d0d",
    "notifications.border": "#1a1a1a",
    "notificationLink.foreground": "#82AAFF",
    "diffEditor.insertedTextBackground": "#1a2a1a33",
    "diffEditor.removedTextBackground": "#2a1a1a33"
  },
  "tokenColors": [
    {
      "scope": ["comment", "punctuation.definition.comment"],
      "settings": {
        "foreground": "#3a3a3a",
        "fontStyle": "italic"
      }
    },
    {
      "scope": ["string", "string.quoted"],
      "settings": {
        "foreground": "#C3E88D"
      }
    },
    {
      "scope": ["constant.numeric", "constant.language", "constant.character"],
      "settings": {
        "foreground": "#F78C6C"
      }
    },
    {
      "scope": ["keyword", "storage.type", "storage.modifier"],
      "settings": {
        "foreground": "#C792EA"
      }
    },
    {
      "scope": ["entity.name.function", "support.function"],
      "settings": {
        "foreground": "#82AAFF"
      }
    },
    {
      "scope": ["entity.name.class", "entity.name.type.class", "support.class"],
      "settings": {
        "foreground": "#FFCB6B"
      }
    },
    {
      "scope": ["variable", "support.variable"],
      "settings": {
        "foreground": "#EEFFFF"
      }
    },
    {
      "scope": ["variable.parameter", "meta.parameters"],
      "settings": {
        "foreground": "#F78C6C",
        "fontStyle": "italic"
      }
    },
    {
      "scope": ["entity.name.tag", "meta.tag"],
      "settings": {
        "foreground": "#F07178"
      }
    },
    {
      "scope": ["entity.other.attribute-name"],
      "settings": {
        "foreground": "#C792EA"
      }
    },
    {
      "scope": ["support.type.property-name"],
      "settings": {
        "foreground": "#82AAFF"
      }
    },
    {
      "scope": ["punctuation"],
      "settings": {
        "foreground": "#89DDFF"
      }
    },
    {
      "scope": ["markup.heading"],
      "settings": {
        "foreground": "#C3E88D",
        "fontStyle": "bold"
      }
    },
    {
      "scope": ["markup.bold"],
      "settings": {
        "fontStyle": "bold",
        "foreground": "#F78C6C"
      }
    },
    {
      "scope": ["markup.italic"],
      "settings": {
        "fontStyle": "italic",
        "foreground": "#C792EA"
      }
    },
    {
      "scope": ["markup.inline.raw"],
      "settings": {
        "foreground": "#C3E88D"
      }
    },
    {
      "scope": ["invalid"],
      "settings": {
        "foreground": "#F07178"
      }
    }
  ]
}
